HydroRoll/__init__.py
HydroRoll/config.py
HydroRoll/exceptions.py
HydroRoll/models/__init__.py
HydroRoll/models/hola.pkl
HydroRoll/models/utils.py
HydroRoll/typing.py
HydroRoll/utils.py
hydroroll-0.1.4.dist-info/METADATA
hydroroll-0.1.4.dist-info/WHEEL
hydroroll-0.1.4.dist-info/licenses/LICENSE
hydroroll-0.1.4.dist-info/RECORD
