Metadata-Version: 2.1
Name: HydroRoll
Version: 0.1.4
Summary: HydroRoll System.
Keywords: bot qq qqbot mirai coolq
Home-page: https://hydroroll.retrofor.space/
Author-Email: 简律纯 <i@jyunko.cn>
License: MIT
Classifier: Development Status :: 5 - Production/Stable
Classifier: Framework :: Robot Framework
Classifier: Framework :: Robot Framework :: Library
Classifier: Operating System :: OS Independent
Classifier: Programming Language :: Python :: 3
Project-URL: Homepage, https://hydroroll.retrofor.space/
Project-URL: Repository, https://github.com/HydroRoll-Team/hydroroll
Project-URL: Documentation, https://hydroroll.retrofor.space/
Requires-Python: >=3.8
Requires-Dist: watchfiles<1.0.0,>=0.18.0
Requires-Dist: joblib>=1.3.2
Requires-Dist: randomgen>=1.26.0
Requires-Dist: jieba>=0.42.1
Requires-Dist: scikit-learn>=1.3.1
Requires-Dist: requests>=2.31.0
Requires-Dist: iamai>=3.2.9
Requires-Dist: iamai-adapter-onebot11>=3.2.9
Requires-Dist: iamai-adapter-kook>=3.2.9
Requires-Dist: iamai-adapter-dingtalk>=3.2.9
Requires-Dist: iamai-adapter-apscheduler>=3.2.9
Requires-Dist: apscheduler>=3.10.4
